hold_this/__init__.py
hold_this/hold_this.py
hold_this-0.1.6.dist-info/LICENSE
hold_this-0.1.6.dist-info/METADATA
hold_this-0.1.6.dist-info/WHEEL
hold_this-0.1.6.dist-info/entry_points.txt
hold_this-0.1.6.dist-info/top_level.txt
hold_this-0.1.6.dist-info/RECORD
