Metadata-Version: 2.1
Name: hold-this
Version: 0.1.6
Summary: hold anything.
Author-email: Soumyo Deep Gupta <deep.main.ac@gmail.com>
Maintainer-email: Soumyo Deep Gupta <deep.main.ac@gmail.com>
License: MIT License
Project-URL: Homepage, https://github.com/d33pster/hold-this
Project-URL: Issues, https://github.com/d33pster/hold-this/issues
Keywords: d33pster,hold,cli-tool,like brew,command,helper
Classifier: Development Status :: 4 - Beta
Classifier: Intended Audience :: Developers
Classifier: Programming Language :: Python :: 3.9
Classifier: Programming Language :: Python :: 3.10
Classifier: Programming Language :: Python :: 3.11
Classifier: Programming Language :: Python :: 3.12
Classifier: License :: OSI Approved :: MIT License
Classifier: Operating System :: OS Independent
Requires-Python: >=3.9
License-File: LICENSE
Requires-Dist: optioner >=1.3.2
